carbon_logger/__init__.py
carbon_logger/decorator.py
carbon_logger-0.0.1.dist-info/METADATA
carbon_logger-0.0.1.dist-info/WHEEL
carbon_logger-0.0.1.dist-info/top_level.txt
carbon_logger-0.0.1.dist-info/RECORD
