Metadata-Version: 2.4
Name: carbon-logger
Version: 0.0.1
Summary: Placeholder release reserving the Carbon Logger Python package name.
Author: CHIMERA
License: MIT
Project-URL: Homepage, https://github.com/scrrlt/carbon-logger-py
Project-URL: Repository, https://github.com/scrrlt/carbon-logger-py
Project-URL: Issues, https://github.com/scrrlt/carbon-logger-py/issues
Keywords: energy,carbon,sustainability,logging,LLM
Classifier: Programming Language :: Python :: 3
Classifier: License :: OSI Approved :: MIT License
Classifier: Operating System :: OS Independent
Requires-Python: >=3.9
